setup.py
assets/doml/assets/__init__.py
src/__init__.py
src/__main__.py
src/data.py
src/requirements.py
src/results.py
src/solver.py
src/synthesis.py
src/types.py
piacere_synthesis-2023.1.0.dist-info/METADATA
piacere_synthesis-2023.1.0.dist-info/WHEEL
piacere_synthesis-2023.1.0.dist-info/RECORD
